README
setup.cfg
setup.py
mod2doctest/__init__.py
mod2doctest/mod2doctest.py
mod2doctest.egg-info/PKG-INFO
mod2doctest.egg-info/SOURCES.txt
mod2doctest.egg-info/dependency_links.txt
mod2doctest.egg-info/top_level.txt