Metadata-Version: 1.0
Name: mod2doctest
Version: 0.2.0
Summary: A way to convert any Python module to a doctest ready doc string.
Home-page: http://packages.python.org/mod2doctest/
Author: Andrew Carter
Author-email: andrewjcarter@gmail.com
License: MIT
Keywords: doctest unit test
Platform: UNKNOWN
Classifier: Development Status :: 3 - Alpha
Classifier: Topic :: Utilities
Classifier: License :: OSI Approved :: MIT License
